dictionaryutils/__init__.py
dictionaryutils/dictionary.py
dictionaryutils/errors.py
dictionaryutils/json_load.py
dictionaryutils/schema_test.py
dictionaryutils/schemas/data_release.yaml
dictionaryutils/schemas/metaschema.yaml
dictionaryutils/schemas/root.yaml
dictionaryutils/version_data.py
dictionaryutils-4.0.0.dist-info/METADATA
dictionaryutils-4.0.0.dist-info/WHEEL
dictionaryutils-4.0.0.dist-info/licenses/LICENSE
dictionaryutils-4.0.0.dist-info/licenses/NOTICE
dictionaryutils-4.0.0.dist-info/RECORD
