Metadata-Version: 2.4
Name: dictionaryutils
Version: 4.0.0
Summary: Python wrapper and metaschema for datadictionary.
License: Apache-2.0
License-File: LICENSE
License-File: NOTICE
Author: CTDS UChicago
Author-email: cdis@uchicago.edu
Requires-Python: >=3.13,<4
Classifier: License :: OSI Approved :: Apache Software License
Classifier: Programming Language :: Python :: 3
Classifier: Programming Language :: Python :: 3.13
Classifier: Programming Language :: Python :: 3.14
Requires-Dist: PyYAML
Requires-Dist: cdislogging
Requires-Dist: gen3dictionary (>=3.0.0)
Requires-Dist: jsonschema (<=4.23.0)
Requires-Dist: requests
Project-URL: Repository, https://github.com/uc-cdis/dictionaryutils
